dnassembly/__init__.py
dnassembly/transformations.py
dnassembly/design/__init__.py
dnassembly/design/primers.py
dnassembly/dna/__init__.py
dnassembly/dna/dna.py
dnassembly/dna/feature.py
dnassembly/dna/part.py
dnassembly/dna/plasmid.py
dnassembly/io/__init__.py
dnassembly/io/genbank.py
dnassembly/io/readas.py
dnassembly/io/snapgene.py
dnassembly/reactions/__init__.py
dnassembly/reactions/cloning.py
dnassembly/reactions/gibson.py
dnassembly/reactions/goldengate.py
dnassembly/reactions/moclo.py
dnassembly/reactions/__pycache__/__init__.cpython-36.pyc
dnassembly/utils/__init__.py
dnassembly/utils/annotation.py
dnassembly/utils/conversion.py
dnassembly/utils/utils.py
dnassembly-0.1.7.dist-info/LICENSE
dnassembly-0.1.7.dist-info/METADATA
dnassembly-0.1.7.dist-info/WHEEL
dnassembly-0.1.7.dist-info/entry_points.txt
dnassembly-0.1.7.dist-info/top_level.txt
dnassembly-0.1.7.dist-info/RECORD
