Metadata-Version: 2.1
Name: dnassembly
Version: 0.1.7
Summary: Digest and assemble DNA
Home-page: https://github.com/jaaamessszzz/DNAssembly
Author: James Lucas
Author-email: james.lucas@berkeley.edu
License: UNKNOWN
Keywords: DNA,assembly,cloning,plasmid,digest,restriction,enzyme,molecular,biology
Platform: UNKNOWN
Classifier: Intended Audience :: Developers
Classifier: Natural Language :: English
Classifier: Programming Language :: Python :: 3
Requires-Dist: networkx
Requires-Dist: biopython
